watermoccasin.py
watermoccasin-1.0.7.dist-info/entry_points.txt
watermoccasin-1.0.7.dist-info/LICENSE
watermoccasin-1.0.7.dist-info/WHEEL
watermoccasin-1.0.7.dist-info/METADATA
watermoccasin-1.0.7.dist-info/RECORD
