Metadata-Version: 2.1
Name: watermoccasin
Version: 1.0.7
Summary: Convert a NPR ONE news feed for offline listening with options for speed up and timed playlist
Author: Alex Reich
Author-email: watermoccasin@alexreich.com
Requires-Python: >=3,<4
Classifier: Programming Language :: Python :: 3
Classifier: Programming Language :: Python :: 3.4
Classifier: Programming Language :: Python :: 3.5
Classifier: Programming Language :: Python :: 3.6
Classifier: Programming Language :: Python :: 3.7
Requires-Dist: algoliasearch (>=1.17.0,<2.0.0)
Requires-Dist: certifi (>=2019.6.16,<2020.0.0)
Requires-Dist: chardet (>=3.0.4,<4.0.0)
Requires-Dist: future (>=0.17.1,<0.18.0)
Requires-Dist: humanfriendly (>=4.18,<5.0)
Requires-Dist: idna (>=2.8,<3.0)
Requires-Dist: mutagen (>=1.42.0,<2.0.0)
Requires-Dist: npr (>=2.3.0,<3.0.0)
Requires-Dist: pydub (>=0.23.1,<0.24.0)
Requires-Dist: requests (>=2.22.0,<3.0.0)
Requires-Dist: urllib3 (>=1.25.3,<2.0.0)
